closely/__init__.py
closely/main.py
closely-19.0.2.dist-info/AUTHORS.rst
closely-19.0.2.dist-info/LICENSE
closely-19.0.2.dist-info/METADATA
closely-19.0.2.dist-info/WHEEL
closely-19.0.2.dist-info/top_level.txt
closely-19.0.2.dist-info/RECORD
