Metadata-Version: 2.1
Name: closely
Version: 19.0.2
Summary: Closely find closest pairs of points, eg duplicates, in a dataset
Home-page: https://github.com/justinshenk/closely
Author: Justin Shenk
Author-email: shenkjustin@gmail.com
Maintainer: Justin Shenk
Maintainer-email: shenkjustin@gmail.com
License: MIT
Keywords: mathematics,geometry,closest pairs,similar data,duplicates
Platform: UNKNOWN
Classifier: Intended Audience :: Developers
Classifier: License :: OSI Approved :: MIT License
Classifier: Intended Audience :: Education
Classifier: Intended Audience :: Science/Research
Classifier: Programming Language :: Python :: 3
Classifier: Programming Language :: Python :: 3.6
Classifier: Topic :: Scientific/Engineering :: Mathematics
Classifier: Topic :: Software Development :: Libraries :: Python Modules
Classifier: Topic :: Software Development :: Libraries
Requires-Python: >= 3.6
Requires-Dist: numpy
Requires-Dist: scipy
Provides-Extra: all
Requires-Dist: matplotlib ; extra == 'all'
Requires-Dist: fastcluster ; extra == 'all'
Provides-Extra: dev
Requires-Dist: coverage ; extra == 'dev'
Requires-Dist: pytest ; extra == 'dev'
Requires-Dist: matplotlib ; extra == 'dev'
Requires-Dist: fastcluster ; extra == 'dev'
Requires-Dist: sphinx ; extra == 'dev'
Requires-Dist: wheel ; extra == 'dev'
Requires-Dist: pre-commit ; extra == 'dev'
Provides-Extra: docs
Requires-Dist: sphinx ; extra == 'docs'
Provides-Extra: tests
Requires-Dist: coverage ; extra == 'tests'
Requires-Dist: pytest ; extra == 'tests'
